README.md
setup.py
src/number_count.py
src/number_count.egg-info/PKG-INFO
src/number_count.egg-info/SOURCES.txt
src/number_count.egg-info/dependency_links.txt
src/number_count.egg-info/requires.txt
src/number_count.egg-info/top_level.txt