Metadata-Version: 2.1
Name: number-count
Version: 0.0.3
Summary: The number-count module makes it simple for you to do number manipulation and perform various operations on numbers.
Home-page: https://github.com/smv1999/number-utility
Author: Vaidhyanathan S M
Author-email: vaidhyanathan.sm@gmail.com
License: UNKNOWN
Platform: UNKNOWN
Classifier: Programming Language :: Python :: 3
Classifier: Programming Language :: Python :: 3.7
Classifier: Programming Language :: Python :: 3.8
Classifier: Topic :: Software Development :: Libraries :: Python Modules
Classifier: License :: OSI Approved :: MIT License
Classifier: Operating System :: OS Independent
Requires-Python: >=3
Provides-Extra: dev
